[{"name":"Simulation","roi":{"DRAM":[{"AVG DBUS CONGESTED CYCLE":23.458922250407685,"REFRESHES ISSUED":545755,"RQ ROW_BUFFER_HIT":8498219,"RQ ROW_BUFFER_MISS":27286926,"WQ ROW_BUFFER_HIT":23693,"WQ ROW_BUFFER_MISS":34167}],"LLC":{"LOAD":{"hit":[14458],"miss":[33814530],"mshr_merge":[0]},"PREFETCH":{"hit":[378],"miss":[1136922],"mshr_merge":[0]},"RFO":{"hit":[79],"miss":[14113],"mshr_merge":[0]},"TRANSLATION":{"hit":[5371],"miss":[819579],"mshr_merge":[0]},"WRITE":{"hit":[58146],"miss":[774],"mshr_merge":[0]},"miss latency":157.00403659592223,"prefetch issued":0,"prefetch requested":0,"useful prefetch":0,"useless prefetch":0},"cores":[{"Avg ROB occupancy at mispredict":116.02125905602715,"cycles":6549062412,"instructions":500000000,"mispredict":{"BRANCH_CONDITIONAL":1602956,"BRANCH_DIRECT_CALL":708,"BRANCH_DIRECT_JUMP":41206,"BRANCH_INDIRECT":0,"BRANCH_INDIRECT_CALL":1,"BRANCH_RETURN":28}}],"cpu0_DTLB":{"LOAD":{"hit":[138030517],"miss":[1501001],"mshr_merge":[814573]},"PREFETCH":{"hit":[0],"miss":[0],"mshr_merge":[0]},"RFO":{"hit":[0],"miss":[0],"mshr_merge":[0]},"TRANSLATION":{"hit":[0],"miss":[0],"mshr_merge":[0]},"WRITE":{"hit":[0],"miss":[0],"mshr_merge":[0]},"miss latency":310.4949739812478,"prefetch issued":0,"prefetch requested":0,"useful prefetch":0,"useless prefetch":0},"cpu0_ITLB":{"LOAD":{"hit":[45736975],"miss":[16],"mshr_merge":[7]},"PREFETCH":{"hit":[0],"miss":[0],"mshr_merge":[0]},"RFO":{"hit":[0],"miss":[0],"mshr_merge":[0]},"TRANSLATION":{"hit":[0],"miss":[0],"mshr_merge":[0]},"WRITE":{"hit":[0],"miss":[0],"mshr_merge":[0]},"miss latency":919.2222222222222,"prefetch issued":0,"prefetch requested":0,"useful prefetch":0,"useless prefetch":0},"cpu0_L1D":{"LOAD":{"hit":[52537743],"miss":[81146632],"mshr_merge":[46171178]},"PREFETCH":{"hit":[0],"miss":[0],"mshr_merge":[0]},"RFO":{"hit":[0],"miss":[0],"mshr_merge":[0]},"TRANSLATION":{"hit":[482575],"miss":[853942],"mshr_merge":[215]},"WRITE":{"hit":[6706205],"miss":[18210],"mshr_merge":[3490]},"miss latency":177.61467648289732,"prefetch issued":0,"prefetch requested":0,"useful prefetch":0,"useless prefetch":0},"cpu0_L1I":{"LOAD":{"hit":[45786802],"miss":[127],"mshr_merge":[16]},"PREFETCH":{"hit":[0],"miss":[0],"mshr_merge":[0]},"RFO":{"hit":[0],"miss":[0],"mshr_merge":[0]},"TRANSLATION":{"hit":[0],"miss":[0],"mshr_merge":[0]},"WRITE":{"hit":[0],"miss":[0],"mshr_merge":[0]},"miss latency":206.74774774774775,"prefetch issued":0,"prefetch requested":0,"useful prefetch":0,"useless prefetch":0},"cpu0_L2C":{"LOAD":{"hit":[610693],"miss":[34364871],"mshr_merge":[535883]},"PREFETCH":{"hit":[786],"miss":[1153816],"mshr_merge":[16516]},"RFO":{"hit":[527],"miss":[14193],"mshr_merge":[1]},"TRANSLATION":{"hit":[28777],"miss":[824950],"mshr_merge":[0]},"WRITE":{"hit":[58355],"miss":[1432],"mshr_merge":[0]},"miss latency":171.69079608618517,"prefetch issued":1154602,"prefetch requested":1154602,"useful prefetch":1107196,"useless prefetch":30104},"cpu0_STLB":{"LOAD":{"hit":[25331],"miss":[661106],"mshr_merge":[0]},"PREFETCH":{"hit":[0],"miss":[0],"mshr_merge":[0]},"RFO":{"hit":[0],"miss":[0],"mshr_merge":[0]},"TRANSLATION":{"hit":[0],"miss":[0],"mshr_merge":[0]},"WRITE":{"hit":[0],"miss":[0],"mshr_merge":[0]},"miss latency":316.2086352264236,"prefetch issued":0,"prefetch requested":0,"useful prefetch":0,"useless prefetch":0}},"sim":{"DRAM":[{"AVG DBUS CONGESTED CYCLE":23.458922250407685,"REFRESHES ISSUED":545755,"RQ ROW_BUFFER_HIT":8498219,"RQ ROW_BUFFER_MISS":27286926,"WQ ROW_BUFFER_HIT":23693,"WQ ROW_BUFFER_MISS":34167}],"LLC":{"LOAD":{"hit":[14458],"miss":[33814530],"mshr_merge":[0]},"PREFETCH":{"hit":[378],"miss":[1136922],"mshr_merge":[0]},"RFO":{"hit":[79],"miss":[14113],"mshr_merge":[0]},"TRANSLATION":{"hit":[5371],"miss":[819579],"mshr_merge":[0]},"WRITE":{"hit":[58146],"miss":[774],"mshr_merge":[0]},"miss latency":157.00403659592223,"prefetch issued":0,"prefetch requested":0,"useful prefetch":0,"useless prefetch":0},"cores":[{"Avg ROB occupancy at mispredict":116.02125905602715,"cycles":6549062412,"instructions":500000000,"mispredict":{"BRANCH_CONDITIONAL":1602956,"BRANCH_DIRECT_CALL":708,"BRANCH_DIRECT_JUMP":41206,"BRANCH_INDIRECT":0,"BRANCH_INDIRECT_CALL":1,"BRANCH_RETURN":28}}],"cpu0_DTLB":{"LOAD":{"hit":[138030517],"miss":[1501001],"mshr_merge":[814573]},"PREFETCH":{"hit":[0],"miss":[0],"mshr_merge":[0]},"RFO":{"hit":[0],"miss":[0],"mshr_merge":[0]},"TRANSLATION":{"hit":[0],"miss":[0],"mshr_merge":[0]},"WRITE":{"hit":[0],"miss":[0],"mshr_merge":[0]},"miss latency":310.4949739812478,"prefetch issued":0,"prefetch requested":0,"useful prefetch":0,"useless prefetch":0},"cpu0_ITLB":{"LOAD":{"hit":[45736975],"miss":[16],"mshr_merge":[7]},"PREFETCH":{"hit":[0],"miss":[0],"mshr_merge":[0]},"RFO":{"hit":[0],"miss":[0],"mshr_merge":[0]},"TRANSLATION":{"hit":[0],"miss":[0],"mshr_merge":[0]},"WRITE":{"hit":[0],"miss":[0],"mshr_merge":[0]},"miss latency":919.2222222222222,"prefetch issued":0,"prefetch requested":0,"useful prefetch":0,"useless prefetch":0},"cpu0_L1D":{"LOAD":{"hit":[52537743],"miss":[81146632],"mshr_merge":[46171178]},"PREFETCH":{"hit":[0],"miss":[0],"mshr_merge":[0]},"RFO":{"hit":[0],"miss":[0],"mshr_merge":[0]},"TRANSLATION":{"hit":[482575],"miss":[853942],"mshr_merge":[215]},"WRITE":{"hit":[6706205],"miss":[18210],"mshr_merge":[3490]},"miss latency":177.61467648289732,"prefetch issued":0,"prefetch requested":0,"useful prefetch":0,"useless prefetch":0},"cpu0_L1I":{"LOAD":{"hit":[45786802],"miss":[127],"mshr_merge":[16]},"PREFETCH":{"hit":[0],"miss":[0],"mshr_merge":[0]},"RFO":{"hit":[0],"miss":[0],"mshr_merge":[0]},"TRANSLATION":{"hit":[0],"miss":[0],"mshr_merge":[0]},"WRITE":{"hit":[0],"miss":[0],"mshr_merge":[0]},"miss latency":206.74774774774775,"prefetch issued":0,"prefetch requested":0,"useful prefetch":0,"useless prefetch":0},"cpu0_L2C":{"LOAD":{"hit":[610693],"miss":[34364871],"mshr_merge":[535883]},"PREFETCH":{"hit":[786],"miss":[1153816],"mshr_merge":[16516]},"RFO":{"hit":[527],"miss":[14193],"mshr_merge":[1]},"TRANSLATION":{"hit":[28777],"miss":[824950],"mshr_merge":[0]},"WRITE":{"hit":[58355],"miss":[1432],"mshr_merge":[0]},"miss latency":171.69079608618517,"prefetch issued":1154602,"prefetch requested":1154602,"useful prefetch":1107196,"useless prefetch":30104},"cpu0_STLB":{"LOAD":{"hit":[25331],"miss":[661106],"mshr_merge":[0]},"PREFETCH":{"hit":[0],"miss":[0],"mshr_merge":[0]},"RFO":{"hit":[0],"miss":[0],"mshr_merge":[0]},"TRANSLATION":{"hit":[0],"miss":[0],"mshr_merge":[0]},"WRITE":{"hit":[0],"miss":[0],"mshr_merge":[0]},"miss latency":316.2086352264236,"prefetch issued":0,"prefetch requested":0,"useful prefetch":0,"useless prefetch":0}},"traces":["traces/602.gcc_s-2226B.champsimtrace.xz"]}]